DCO
LICENSE
MAINTAINERS
MANIFEST.in
README.md
requirements.txt
setup.py
bblfsh/__init__.py
bblfsh/aliases.py
bblfsh/client.py
bblfsh/compat.py
bblfsh/launcher.py
bblfsh/node.py
bblfsh/node_iterator.py
bblfsh/pyuast.cc
bblfsh/result_context.py
bblfsh/roles.py
bblfsh/test.py
bblfsh/test_compat.py
bblfsh/tree_order.py
bblfsh/type_aliases.py
bblfsh.egg-info/PKG-INFO
bblfsh.egg-info/SOURCES.txt
bblfsh.egg-info/dependency_links.txt
bblfsh.egg-info/not-zip-safe
bblfsh.egg-info/requires.txt
bblfsh.egg-info/top_level.txt
bblfsh/github/__init__.py
bblfsh/github/com/__init__.py
bblfsh/github/com/gogo/__init__.py
bblfsh/github/com/gogo/protobuf/__init__.py
bblfsh/github/com/gogo/protobuf/gogoproto/__init__.py
bblfsh/github/com/gogo/protobuf/gogoproto/gogo_pb2.py
bblfsh/gopkg/__init__.py
bblfsh/gopkg/in/__init__.py
bblfsh/gopkg/in/bblfsh/__init__.py
bblfsh/gopkg/in/bblfsh/sdk/__init__.py
bblfsh/gopkg/in/bblfsh/sdk/v1/__init__.py
bblfsh/gopkg/in/bblfsh/sdk/v1/protocol/__init__.py
bblfsh/gopkg/in/bblfsh/sdk/v1/protocol/generated_pb2.py
bblfsh/gopkg/in/bblfsh/sdk/v1/protocol/generated_pb2_grpc.py
bblfsh/gopkg/in/bblfsh/sdk/v1/uast/__init__.py
bblfsh/gopkg/in/bblfsh/sdk/v1/uast/generated_pb2.py
bblfsh/gopkg/in/bblfsh/sdk/v2/__init__.py
bblfsh/gopkg/in/bblfsh/sdk/v2/protocol/__init__.py
bblfsh/gopkg/in/bblfsh/sdk/v2/protocol/generated_pb2.py
bblfsh/gopkg/in/bblfsh/sdk/v2/protocol/generated_pb2_grpc.py
bblfsh/gopkg/in/bblfsh/sdk/v2/uast/__init__.py
bblfsh/gopkg/in/bblfsh/sdk/v2/uast/generated_pb2.py