Metadata-Version: 1.2
Name: bblfsh
Version: 4.2.0
Summary: Fetches Universal Abstract Syntax Trees from Babelfish.
Home-page: https://github.com/bblfsh/python-client
Author: source{d}
Author-email: language-analysis@sourced.tech
License: Apache 2.0
Download-URL: https://github.com/bblfsh/python-client
Keywords: babelfish,uast
Platform: UNKNOWN
Classifier: Development Status :: 3 - Alpha
Classifier: Environment :: Console
Classifier: Intended Audience :: Developers
Classifier: License :: OSI Approved :: Apache Software License
Classifier: Operating System :: POSIX
Classifier: Programming Language :: Python :: 3.6
Classifier: Programming Language :: Python :: 3.7
Classifier: Topic :: Software Development :: Libraries
Requires-Python: >=3.6
